zmon_worker-0.1.dist-info/DESCRIPTION.rst
zmon_worker-0.1.dist-info/METADATA
zmon_worker-0.1.dist-info/RECORD
zmon_worker-0.1.dist-info/WHEEL
zmon_worker-0.1.dist-info/entry_points.txt
zmon_worker-0.1.dist-info/metadata.json
zmon_worker-0.1.dist-info/top_level.txt
zmon_worker_monitor/__init__.py
zmon_worker_monitor/__main__.py
zmon_worker_monitor/emu_kombu.py
zmon_worker_monitor/eventloghttp.py
zmon_worker_monitor/plugin_manager.py
zmon_worker_monitor/process_controller.py
zmon_worker_monitor/redis_context_manager.py
zmon_worker_monitor/rpc_client.py
zmon_worker_monitor/rpc_server.py
zmon_worker_monitor/rpc_utils.py
zmon_worker_monitor/settings.py
zmon_worker_monitor/settings_pro.py
zmon_worker_monitor/tasks.py
zmon_worker_monitor/web.py
zmon_worker_monitor/worker.py
zmon_worker_monitor/workflow.py
zmon_worker_monitor/adapters/__init__.py
zmon_worker_monitor/adapters/ibase_plugin.py
zmon_worker_monitor/adapters/ifunctionfactory_plugin.py
zmon_worker_monitor/builtins/__init__.py
zmon_worker_monitor/builtins/plugins/__init__.py
zmon_worker_monitor/builtins/plugins/cassandra_wrapper.py
zmon_worker_monitor/builtins/plugins/cassandra_wrapper.worker_plugin
zmon_worker_monitor/builtins/plugins/checkldap.py
zmon_worker_monitor/builtins/plugins/checkldap.worker_plugin
zmon_worker_monitor/builtins/plugins/cloudwatch.py
zmon_worker_monitor/builtins/plugins/cloudwatch.worker_plugin
zmon_worker_monitor/builtins/plugins/counter.py
zmon_worker_monitor/builtins/plugins/counter.worker_plugin
zmon_worker_monitor/builtins/plugins/distance_to_history.py
zmon_worker_monitor/builtins/plugins/eventlog.py
zmon_worker_monitor/builtins/plugins/eventlog.worker_plugin
zmon_worker_monitor/builtins/plugins/exasol.py
zmon_worker_monitor/builtins/plugins/exasol.worker_plugin
zmon_worker_monitor/builtins/plugins/exceptions_.py
zmon_worker_monitor/builtins/plugins/exceptions_.worker_plugin
zmon_worker_monitor/builtins/plugins/history.py
zmon_worker_monitor/builtins/plugins/history.worker_plugin
zmon_worker_monitor/builtins/plugins/http.py
zmon_worker_monitor/builtins/plugins/http.worker_plugin
zmon_worker_monitor/builtins/plugins/jmx.py
zmon_worker_monitor/builtins/plugins/jmx.worker_plugin
