Metadata-Version: 2.0
Name: zmon-worker
Version: 0.1
Summary: ZMON Worker Monitor
Home-page: https://github.com/zalando/zmon-worker
Author: Henning Jacobs
Author-email: henning.jacobs@zalando.de
License: Apache License 2.0
Keywords: zalando zmon zmon2 worker component monitoring infrastructure
Platform: All
Classifier: Development Status :: 5 - Production/Stable
Classifier: Intended Audience :: Developers
Classifier: License :: OSI Approved :: Apache Software License
Classifier: Operating System :: OS Independent
Classifier: Programming Language :: Python
Classifier: Programming Language :: Python :: 2
Classifier: Topic :: Software Development :: Libraries :: Python Modules
Requires-Dist: CherryPy
Requires-Dist: Jinja2
Requires-Dist: MarkupSafe
Requires-Dist: PyMySQL (==0.6.1)
Requires-Dist: PyYAML
Requires-Dist: Yapsy (>=1.10.423)
Requires-Dist: boto3
Requires-Dist: cassandra-driver (==2.7.2)
Requires-Dist: dnspython
Requires-Dist: dogpile.cache
Requires-Dist: eventlog-writer (==0.4.5)
Requires-Dist: functional
Requires-Dist: numpy
Requires-Dist: prometheus-client
Requires-Dist: psycopg2
Requires-Dist: pymongo (==3.0.3)
Requires-Dist: pysnmp
Requires-Dist: python-ldap (==2.4.19)
Requires-Dist: python-snappy
Requires-Dist: pythonwhois (==2.4.3)
Requires-Dist: pytz
Requires-Dist: redis
Requires-Dist: requests
Requires-Dist: setproctitle
Requires-Dist: stups-tokens
Requires-Dist: subprocess32
Requires-Dist: suds
Requires-Dist: timeperiod2 (==0.1)
